meduza.py
meduza-18.7.dist-info/METADATA
meduza-18.7.dist-info/RECORD
meduza-18.7.dist-info/WHEEL
meduza-18.7.dist-info/top_level.txt
