Metadata-Version: 2.1
Name: meduza
Version: 18.7
Summary: A simple Python module that wraps the meduza.io API.
Home-page: https://github.com/dmkskn/meduza
Author: Dima Koskin
Author-email: dmksknn@gmail.com
License: MIT
Keywords: meduza media wrapper russia english russian
Platform: UNKNOWN
Classifier: License :: OSI Approved :: MIT License
Classifier: Programming Language :: Python
Classifier: Programming Language :: Python :: 3
Classifier: Programming Language :: Python :: 3.6
Classifier: Programming Language :: Python :: 3 :: Only
Requires-Python: >=3.6
